chapter_05/extend_test_framework/calculator_plugin/__init__.py
chapter_05/extend_test_framework/calculator_plugin/calculator_plugin.py
pytest_demo_plugin-1.0.1.dist-info/METADATA
pytest_demo_plugin-1.0.1.dist-info/WHEEL
pytest_demo_plugin-1.0.1.dist-info/entry_points.txt
pytest_demo_plugin-1.0.1.dist-info/top_level.txt
pytest_demo_plugin-1.0.1.dist-info/RECORD
